<?xml version="1.0" encoding="utf-8"?>
<resources>
    <color name="quick_send_active_background_color">@*com.google.android.talk:color/accent</color>
    <color name="accept_button_text_color">@*com.google.android.talk:color/accent</color>
    <color name="settings_action_bar_background_color">@*com.google.android.talk:color/accent</color>
    <color name="feedback_color">@*com.google.android.talk:color/accent</color>
    <color name="people_list_section_header">@*com.google.android.talk:color/accent</color>
    <color name="edit_participants_toolbar_color">@*com.google.android.talk:color/accent</color>
    <color name="edit_participants_statusbar_color">@*com.google.android.talk:color/accent</color>
    <color name="floating_action_button_pressed_color">@*com.google.android.talk:color/accent</color>
    <color name="floating_action_button_unpressed_color">@*com.google.android.talk:color/accent</color>
    <color name="indicator_color">@*com.google.android.talk:color/accent</color>
    <color name="fab_hangouts_primary_color">@*com.google.android.talk:color/accent</color>
    <color name="callerid_blue">@*com.google.android.talk:color/accent</color>
    <color name="image_selected_stroke">@*com.google.android.talk:color/accent</color>
    <color name="generic_selected_item">@*com.google.android.talk:color/accent</color>
    <color name="text_blue">@*com.google.android.talk:color/accent</color>
    <color name="blue_4">@*com.google.android.talk:color/accent</color>
    <color name="search_query_highlight_color">@*com.google.android.talk:color/accent</color>
    <color name="accent_light">@*com.google.android.talk:color/accent</color>
    <color name="accent_dark">@*com.google.android.talk:color/accent</color>
    <color name="bg_item_normal_invite">@*com.google.android.talk:color/accent</color>
    <color name="bg_item_activated">@*com.google.android.talk:color/accent</color>
    <color name="bg_item_selected">@*com.google.android.talk:color/accent</color>
    <color name="bg_item_pressed">@*com.google.android.talk:color/accent</color>
    <color name="quantum_googgreen400">@*com.google.android.talk:color/accent</color>
    <color name="quantum_googgreen500">@*com.google.android.talk:color/accent</color>
    <color name="quantum_googgreen600">@*com.google.android.talk:color/accent</color>
    <color name="quantum_googgreen700">@*com.google.android.talk:color/accent</color>
    <color name="quantum_googgreen800">@*com.google.android.talk:color/accent</color>
    <color name="quantum_googgreenA200">@*com.google.android.talk:color/accent</color>
    <color name="quantum_vanillagreenA200">@*com.google.android.talk:color/accent</color>
    <color name="abc_search_url_text_normal">@*com.google.android.talk:color/accent</color>
    <color name="accent_material_light">@*com.google.android.talk:color/accent</color><!--TODO-->
    <color name="accent_material_dark">@*com.google.android.talk:color/accent</color>
    <color name="material_grey_50">@*com.google.android.talk:color/accent</color>
    <color name="material_deep_teal_200">@*com.google.android.talk:color/accent</color>
    <color name="material_deep_teal_500">@*com.google.android.talk:color/accent</color>
    <color name="material_blue_grey_800">@*com.google.android.talk:color/accent</color>
    <color name="material_blue_grey_900">@*com.google.android.talk:color/accent</color>
    <color name="material_blue_grey_950">@*com.google.android.talk:color/accent</color>
    <color name="solid_green">@*com.google.android.talk:color/accent</color>
    <color name="transparent_green">@*com.google.android.talk:color/accent</color>
    <color name="dark_green">@*com.google.android.talk:color/accent</color>
    <color name="light_green">@*com.google.android.talk:color/accent</color>
    <color name="hangouts_search_query_highlight_color">@*com.google.android.talk:color/accent</color>
    <color name="section_header_color">@*com.google.android.talk:color/accent</color>
    <color name="photo_selection_color">@*com.google.android.talk:color/accent</color>
    <color name="ongoing_hangout_background">@*com.google.android.talk:color/accent</color>
    <color name="ongoing_hangout_background_v2">@*com.google.android.talk:color/accent</color>
    <color name="bg_item_pressed_v2">@*com.google.android.talk:color/accent</color>
    <color name="hangout_calling_participants_count">@*com.google.android.talk:color/accent</color>
    <color name="hangout_volume_dot">@*com.google.android.talk:color/accent</color>
    <color name="hangout_fmf_in_call_promo_eligible">@*com.google.android.talk:color/accent</color>
    <color name="pressed_bg">@*com.google.android.talk:color/accent</color>
    <color name="conversation_hangout_color">@*com.google.android.talk:color/accent</color>
    <color name="status_message_statusbar_color">@*com.google.android.talk:color/accent</color>
    <color name="status_message_background">@*com.google.android.talk:color/accent</color>
    <color name="dialpad_primary_text_color">@*com.google.android.talk:color/accent</color>
    <color name="dialpad_calling_rates_text_highlight_color">@*com.google.android.talk:color/accent</color>
    <color name="android_auto_default_color">@*com.google.android.talk:color/accent</color>
    <color name="alert_dialog_hyperlink">@*com.google.android.talk:color/accent</color>
    <color name="hangouts_primary_color">@*com.google.android.talk:color/accent</color>
    <color name="reply_view_action_button_text">@*com.google.android.talk:color/accent</color>
    <color name="default_button_text_color">@*com.google.android.talk:color/accent</color>
    <color name="highlight_button_background_color">@*com.google.android.talk:color/accent</color>
    <color name="dialog_accent_color">@*com.google.android.talk:color/accent</color>
    <color name="edit_participants_toolbar_color_one_on_one">@*com.google.android.talk:color/accent</color>
    <color name="edit_participants_statusbar_color_one_on_one">@*com.google.android.talk:color/accent</color>
    <color name="volume_dot">@*com.google.android.talk:color/accent</color>
    <color name="notification_action_color_filter">@*com.google.android.talk:color/accent</color>
    <color name="outgoing_conversation_bubble_background">@*com.google.android.talk:color/accent</color>
    <color name="outgoing_conversation_bubble_background_otr">@*com.google.android.talk:color/accent</color>
    <color name="in_call_message_link">@*com.google.android.talk:color/accent</color>
    <color name="in_call_message_indicator_background">@*com.google.android.talk:color/accent</color>
</resources>
